[
  {
    "Patient": {
      "IllnessType": 2,
      "AdditionalInfo": "New Gerpis",
      "Address": "new super adress",
      "Name": "New Vasya",
      "Surname": "",
      "Phone": null,
      "Email": null,
      "Id": 1,
      "CreatedAt": "2024-10-29T00:20:09.5637083+02:00",
      "UpdatedAt": "2024-10-29T00:23:33.1271839+02:00"
    },
    "Doctor": {
      "DoctorType": 3,
      "Experience": 22,
      "Salary": 333.0,
      "Name": "Richi",
      "Surname": "",
      "Phone": null,
      "Email": null,
      "Id": 2,
      "CreatedAt": "2024-10-29T00:14:53.4998832+02:00",
      "UpdatedAt": "0001-01-01T00:00:00"
    },
    "DateTimeFrom": "2024-10-29T16:00:00",
    "DateTimeTo": "2024-10-29T16:30:00",
    "Description": "First visit",
    "Id": 1,
    "CreatedAt": "2024-10-29T22:40:13.6113271+02:00",
    "UpdatedAt": "0001-01-01T00:00:00"
  }
]